rcmdow/__init__.py
rcmdow/core/__init__.py
rcmdow/core/cmdow.py
rcmdow/core/display/__init__.py
rcmdow/core/display/plconfig.py
rcmdow/core/winresize.py
rcmdow/main.py
rcmdow-0.1.0.dist-info/entry_points.txt
rcmdow-0.1.0.dist-info/METADATA
rcmdow-0.1.0.dist-info/WHEEL
rcmdow-0.1.0.dist-info/RECORD
