Metadata-Version: 2.1
Name: rcmdow
Version: 0.1.0
Summary: A rich python wrapper on the CMDOW window util
License: MIT
Author: arnos-stuff
Author-email: bcda0276@gmail.com
Requires-Python: >=3.8,<4.0
Classifier: License :: OSI Approved :: MIT License
Classifier: Programming Language :: Python :: 3
Classifier: Programming Language :: Python :: 3.8
Classifier: Programming Language :: Python :: 3.9
Classifier: Programming Language :: Python :: 3.10
Classifier: Programming Language :: Python :: 3.11
Requires-Dist: polars (>=0.15.6,<0.16.0)
Requires-Dist: psutil (>=5.9.4,<6.0.0)
Requires-Dist: pywin32 (>=305,<306)
Requires-Dist: rich (>=12.6.0,<13.0.0)
Requires-Dist: typer[all] (>=0.7.0,<0.8.0)
Requires-Dist: windows-curses (>=2.3.1,<3.0.0)
